{
	"$schema": "http://schema.management.azure.com/schemas/2015-01-01/deploymentTemplate.json#",
	"contentVersion": "1.0.0.0",
	"parameters": {
		"factoryName": {
			"type": "string",
			"metadata": "Data Factory name",
			"defaultValue": "QuantCloudDataFactory"
		},
		"LS_ADLS_CSV_accountKey": {
			"type": "secureString",
			"metadata": "Secure string for 'accountKey' of 'LS_ADLS_CSV'"
		},
		"LS_AZURE_SQL_DATABASE_password": {
			"type": "secureString",
			"metadata": "Secure string for 'password' of 'LS_AZURE_SQL_DATABASE'"
		},
		"LS_ADLS_CSV_properties_typeProperties_url": {
			"type": "string",
			"defaultValue": "https://rainbowstorageadls.dfs.core.windows.net/"
		},
		"LS_AZURE_SQL_DATABASE_properties_typeProperties_server": {
			"type": "string",
			"defaultValue": "quant-cloud-server.database.windows.net"
		},
		"LS_AZURE_SQL_DATABASE_properties_typeProperties_database": {
			"type": "string",
			"defaultValue": "QuantCloudDB"
		},
		"LS_AZURE_SQL_DATABASE_properties_typeProperties_userName": {
			"type": "string",
			"defaultValue": "QuantCloud"
		},
		"MyEventBasedTrigger_properties_PL_EVENT_BASED_MIGRATION_parameters_FileName": {
			"type": "string",
			"defaultValue": "@triggerBody().fileName"
		},
		"MyEventBasedTrigger_properties_typeProperties_scope": {
			"type": "string",
			"defaultValue": "/subscriptions/55a823ff-3572-4afe-84f3-2631597109ef/resourceGroups/rg_rainbow/providers/Microsoft.Storage/storageAccounts/rainbowstorageadls"
		}
	},
	"variables": {
		"factoryId": "[concat('Microsoft.DataFactory/factories/', parameters('factoryName'))]"
	},
	"resources": [
		{
			"name": "[concat(parameters('factoryName'), '/PL_COPY_ACTIVITY')]",
			"type": "Microsoft.DataFactory/factories/pipelines",
			"apiVersion": "2018-06-01",
			"properties": {
				"activities": [
					{
						"name": "CopyCsvFileToAdls",
						"type": "Copy",
						"dependsOn": [],
						"policy": {
							"timeout": "0.12:00:00",
							"retry": 0,
							"retryIntervalInSeconds": 30,
							"secureOutput": false,
							"secureInput": false
						},
						"userProperties": [],
						"typeProperties": {
							"source": {
								"type": "DelimitedTextSource",
								"storeSettings": {
									"type": "AzureBlobFSReadSettings",
									"recursive": true,
									"enablePartitionDiscovery": false
								},
								"formatSettings": {
									"type": "DelimitedTextReadSettings"
								}
							},
							"sink": {
								"type": "DelimitedTextSink",
								"storeSettings": {
									"type": "AzureBlobFSWriteSettings"
								},
								"formatSettings": {
									"type": "DelimitedTextWriteSettings",
									"quoteAllText": true,
									"fileExtension": ".txt"
								}
							},
							"enableStaging": false,
							"translator": {
								"type": "TabularTranslator",
								"mappings": [
									{
										"source": {
											"name": "Constituency Number",
											"type": "String",
											"physicalType": "String"
										},
										"sink": {
											"name": "ConstituencyNumber",
											"physicalType": "String"
										}
									},
									{
										"source": {
											"name": "Constituency Name",
											"type": "String",
											"physicalType": "String"
										},
										"sink": {
											"name": "ConstituencyName",
											"physicalType": "String"
										}
									},
									{
										"source": {
											"name": "Serial Number",
											"type": "String",
											"physicalType": "String"
										},
										"sink": {
											"name": "SerialNumber",
											"physicalType": "String"
										}
									},
									{
										"source": {
											"name": "Candidate Name",
											"type": "String",
											"physicalType": "String"
										},
										"sink": {
											"name": "CandidateName",
											"physicalType": "String"
										}
									},
									{
										"source": {
											"name": "Party",
											"type": "String",
											"physicalType": "String"
										},
										"sink": {
											"name": "Party",
											"type": "String",
											"physicalType": "String"
										}
									},
									{
										"source": {
											"name": "EVM Votes",
											"type": "String",
											"physicalType": "String"
										},
										"sink": {
											"name": "EVMVotes",
											"physicalType": "String"
										}
									},
									{
										"source": {
											"name": "Postal Votes",
											"type": "String",
											"physicalType": "String"
										},
										"sink": {
											"name": "PostalVotes",
											"physicalType": "String"
										}
									},
									{
										"source": {
											"name": "Total Votes",
											"type": "String",
											"physicalType": "String"
										},
										"sink": {
											"name": "TotalVotes",
											"physicalType": "String"
										}
									},
									{
										"source": {
											"name": "Vote Percentage",
											"type": "String",
											"physicalType": "String"
										},
										"sink": {
											"name": "VotePercentage",
											"physicalType": "String"
										}
									}
								],
								"typeConversion": true,
								"typeConversionSettings": {
									"allowDataTruncation": true,
									"treatBooleanAsNumber": false
								}
							}
						},
						"inputs": [
							{
								"referenceName": "DS_READ_CSV",
								"type": "DatasetReference",
								"parameters": {}
							}
						],
						"outputs": [
							{
								"referenceName": "DS_CSV_TARGET",
								"type": "DatasetReference",
								"parameters": {}
							}
						]
					},
					{
						"name": "DeleteFile",
						"type": "Delete",
						"dependsOn": [
							{
								"activity": "CopyCsvFileToAdls",
								"dependencyConditions": [
									"Succeeded"
								]
							}
						],
						"policy": {
							"timeout": "0.12:00:00",
							"retry": 0,
							"retryIntervalInSeconds": 30,
							"secureOutput": false,
							"secureInput": false
						},
						"userProperties": [],
						"typeProperties": {
							"dataset": {
								"referenceName": "DS_READ_CSV",
								"type": "DatasetReference",
								"parameters": {}
							},
							"enableLogging": false,
							"storeSettings": {
								"type": "AzureBlobFSReadSettings",
								"recursive": true,
								"enablePartitionDiscovery": false
							}
						}
					}
				],
				"policy": {
					"elapsedTimeMetric": {}
				},
				"annotations": []
			},
			"dependsOn": [
				"[concat(variables('factoryId'), '/datasets/DS_READ_CSV')]",
				"[concat(variables('factoryId'), '/datasets/DS_CSV_TARGET')]"
			]
		},
		{
			"name": "[concat(parameters('factoryName'), '/PL_COPY_FILES_DYNAMICALLY')]",
			"type": "Microsoft.DataFactory/factories/pipelines",
			"apiVersion": "2018-06-01",
			"properties": {
				"activities": [
					{
						"name": "GetMetadataInfo",
						"type": "GetMetadata",
						"dependsOn": [],
						"policy": {
							"timeout": "0.12:00:00",
							"retry": 0,
							"retryIntervalInSeconds": 30,
							"secureOutput": false,
							"secureInput": false
						},
						"userProperties": [],
						"typeProperties": {
							"dataset": {
								"referenceName": "DS_FILE_LOOKUP",
								"type": "DatasetReference",
								"parameters": {}
							},
							"fieldList": [
								"childItems"
							],
							"storeSettings": {
								"type": "AzureBlobFSReadSettings",
								"recursive": true,
								"enablePartitionDiscovery": false
							},
							"formatSettings": {
								"type": "BinaryReadSettings"
							}
						}
					},
					{
						"name": "FilterCsvFiles",
						"type": "Filter",
						"dependsOn": [
							{
								"activity": "GetMetadataInfo",
								"dependencyConditions": [
									"Succeeded"
								]
							}
						],
						"userProperties": [],
						"typeProperties": {
							"items": {
								"value": "@activity('GetMetadataInfo').output.childItems",
								"type": "Expression"
							},
							"condition": {
								"value": "@endswith(item().name, '.csv')",
								"type": "Expression"
							}
						}
					},
					{
						"name": "ForEachCsvFile",
						"type": "ForEach",
						"dependsOn": [
							{
								"activity": "FilterCsvFiles",
								"dependencyConditions": [
									"Succeeded"
								]
							}
						],
						"userProperties": [],
						"typeProperties": {
							"items": {
								"value": "@activity('FilterCsvFiles').output.Value",
								"type": "Expression"
							},
							"isSequential": false,
							"batchCount": 5,
							"activities": [
								{
									"name": "CopyDynamicCsvFile",
									"type": "Copy",
									"dependsOn": [],
									"policy": {
										"timeout": "0.12:00:00",
										"retry": 0,
										"retryIntervalInSeconds": 30,
										"secureOutput": false,
										"secureInput": false
									},
									"userProperties": [],
									"typeProperties": {
										"source": {
											"type": "BinarySource",
											"storeSettings": {
												"type": "AzureBlobFSReadSettings",
												"recursive": true
											},
											"formatSettings": {
												"type": "BinaryReadSettings"
											}
										},
										"sink": {
											"type": "BinarySink",
											"storeSettings": {
												"type": "AzureBlobFSWriteSettings"
											}
										},
										"enableStaging": false
									},
									"inputs": [
										{
											"referenceName": "DS_DYNAMIC_CSV_FILE_MIGRATION",
											"type": "DatasetReference",
											"parameters": {
												"FileName": {
													"value": "@item().name",
													"type": "Expression"
												}
											}
										}
									],
									"outputs": [
										{
											"referenceName": "DS_DYNAMIC_CSV_FILE_MIGRATION_TARGET",
											"type": "DatasetReference",
											"parameters": {
												"TargetFileName": {
													"value": "@item().name",
													"type": "Expression"
												}
											}
										}
									]
								},
								{
									"name": "DeleteDynamicCsvFile_copy1",
									"type": "Delete",
									"dependsOn": [
										{
											"activity": "CopyDynamicCsvFile",
											"dependencyConditions": [
												"Succeeded"
											]
										}
									],
									"policy": {
										"timeout": "0.12:00:00",
										"retry": 0,
										"retryIntervalInSeconds": 30,
										"secureOutput": false,
										"secureInput": false
									},
									"userProperties": [],
									"typeProperties": {
										"dataset": {
											"referenceName": "DS_DYNAMIC_CSV_FILE_MIGRATION",
											"type": "DatasetReference",
											"parameters": {
												"FileName": {
													"value": "@item().name",
													"type": "Expression"
												}
											}
										},
										"enableLogging": false,
										"storeSettings": {
											"type": "AzureBlobFSReadSettings",
											"recursive": true,
											"enablePartitionDiscovery": false
										}
									}
								}
							]
						}
					}
				],
				"policy": {
					"elapsedTimeMetric": {}
				},
				"annotations": []
			},
			"dependsOn": [
				"[concat(variables('factoryId'), '/datasets/DS_FILE_LOOKUP')]",
				"[concat(variables('factoryId'), '/datasets/DS_DYNAMIC_CSV_FILE_MIGRATION')]",
				"[concat(variables('factoryId'), '/datasets/DS_DYNAMIC_CSV_FILE_MIGRATION_TARGET')]"
			]
		},
		{
			"name": "[concat(parameters('factoryName'), '/PL_COPY_FILES_TO_DYNAMIC_LOCATION')]",
			"type": "Microsoft.DataFactory/factories/pipelines",
			"apiVersion": "2018-06-01",
			"properties": {
				"activities": [
					{
						"name": "GetFileMetadataInfo",
						"type": "GetMetadata",
						"dependsOn": [],
						"policy": {
							"timeout": "0.12:00:00",
							"retry": 0,
							"retryIntervalInSeconds": 30,
							"secureOutput": false,
							"secureInput": false
						},
						"userProperties": [],
						"typeProperties": {
							"dataset": {
								"referenceName": "DS_FILE_LOOKUP",
								"type": "DatasetReference",
								"parameters": {}
							},
							"fieldList": [
								"childItems"
							],
							"storeSettings": {
								"type": "AzureBlobFSReadSettings",
								"recursive": true,
								"enablePartitionDiscovery": false
							},
							"formatSettings": {
								"type": "BinaryReadSettings"
							}
						}
					},
					{
						"name": "ForEachFile",
						"type": "ForEach",
						"dependsOn": [
							{
								"activity": "GetFileMetadataInfo",
								"dependencyConditions": [
									"Succeeded"
								]
							}
						],
						"userProperties": [],
						"typeProperties": {
							"items": {
								"value": "@activity('GetFileMetadataInfo').output.childItems",
								"type": "Expression"
							},
							"isSequential": false,
							"batchCount": 10,
							"activities": [
								{
									"name": "IfTypeIsFile",
									"type": "IfCondition",
									"dependsOn": [],
									"userProperties": [],
									"typeProperties": {
										"expression": {
											"value": "@equals(item().type, 'File')",
											"type": "Expression"
										},
										"ifTrueActivities": [
											{
												"name": "CopyFiles",
												"type": "Copy",
												"dependsOn": [],
												"policy": {
													"timeout": "0.12:00:00",
													"retry": 0,
													"retryIntervalInSeconds": 30,
													"secureOutput": false,
													"secureInput": false
												},
												"userProperties": [],
												"typeProperties": {
													"source": {
														"type": "BinarySource",
														"storeSettings": {
															"type": "AzureBlobFSReadSettings",
															"recursive": true
														},
														"formatSettings": {
															"type": "BinaryReadSettings"
														}
													},
													"sink": {
														"type": "BinarySink",
														"storeSettings": {
															"type": "AzureBlobFSWriteSettings"
														}
													},
													"enableStaging": false
												},
												"inputs": [
													{
														"referenceName": "DS_SOURCE_FILE_POINTER",
														"type": "DatasetReference",
														"parameters": {
															"SrcFileName": {
																"value": "@item().name",
																"type": "Expression"
															}
														}
													}
												],
												"outputs": [
													{
														"referenceName": "DS_TARGET_FILE_POINTER",
														"type": "DatasetReference",
														"parameters": {
															"TrgFileName": {
																"value": "@item().name",
																"type": "Expression"
															},
															"TrgFolderName": {
																"value": "@split(item().name, '.')[1]",
																"type": "Expression"
															}
														}
													}
												]
											},
											{
												"name": "DeleteFiles",
												"type": "Delete",
												"dependsOn": [
													{
														"activity": "CopyFiles",
														"dependencyConditions": [
															"Succeeded"
														]
													}
												],
												"policy": {
													"timeout": "0.12:00:00",
													"retry": 0,
													"retryIntervalInSeconds": 30,
													"secureOutput": false,
													"secureInput": false
												},
												"userProperties": [],
												"typeProperties": {
													"dataset": {
														"referenceName": "DS_SOURCE_FILE_POINTER",
														"type": "DatasetReference",
														"parameters": {
															"SrcFileName": {
																"value": "@item().name",
																"type": "Expression"
															}
														}
													},
													"enableLogging": false,
													"storeSettings": {
														"type": "AzureBlobFSReadSettings",
														"recursive": true,
														"enablePartitionDiscovery": false
													}
												}
											}
										]
									}
								}
							]
						}
					}
				],
				"policy": {
					"elapsedTimeMetric": {}
				},
				"annotations": []
			},
			"dependsOn": [
				"[concat(variables('factoryId'), '/datasets/DS_FILE_LOOKUP')]",
				"[concat(variables('factoryId'), '/datasets/DS_SOURCE_FILE_POINTER')]",
				"[concat(variables('factoryId'), '/datasets/DS_TARGET_FILE_POINTER')]"
			]
		},
		{
			"name": "[concat(parameters('factoryName'), '/PL_EVENT_BASED_MIGRATION')]",
			"type": "Microsoft.DataFactory/factories/pipelines",
			"apiVersion": "2018-06-01",
			"properties": {
				"activities": [
					{
						"name": "CopyFiles",
						"type": "Copy",
						"dependsOn": [],
						"policy": {
							"timeout": "0.12:00:00",
							"retry": 0,
							"retryIntervalInSeconds": 30,
							"secureOutput": false,
							"secureInput": false
						},
						"userProperties": [],
						"typeProperties": {
							"source": {
								"type": "DelimitedTextSource",
								"storeSettings": {
									"type": "AzureBlobFSReadSettings",
									"recursive": true,
									"enablePartitionDiscovery": false
								},
								"formatSettings": {
									"type": "DelimitedTextReadSettings"
								}
							},
							"sink": {
								"type": "DelimitedTextSink",
								"storeSettings": {
									"type": "AzureBlobFSWriteSettings"
								},
								"formatSettings": {
									"type": "DelimitedTextWriteSettings",
									"quoteAllText": true,
									"fileExtension": ".txt"
								}
							},
							"enableStaging": false,
							"translator": {
								"type": "TabularTranslator",
								"typeConversion": true,
								"typeConversionSettings": {
									"allowDataTruncation": true,
									"treatBooleanAsNumber": false
								}
							}
						},
						"inputs": [
							{
								"referenceName": "DS_SOURCE_CSV",
								"type": "DatasetReference",
								"parameters": {
									"SourceFileName": {
										"value": "@pipeline().parameters.FileName",
										"type": "Expression"
									}
								}
							}
						],
						"outputs": [
							{
								"referenceName": "DS_TARGET_CSV",
								"type": "DatasetReference",
								"parameters": {
									"TargetFileName": {
										"value": "@pipeline().parameters.FileName",
										"type": "Expression"
									}
								}
							}
						]
					}
				],
				"policy": {
					"elapsedTimeMetric": {}
				},
				"parameters": {
					"FileName": {
						"type": "string"
					}
				},
				"annotations": []
			},
			"dependsOn": [
				"[concat(variables('factoryId'), '/datasets/DS_SOURCE_CSV')]",
				"[concat(variables('factoryId'), '/datasets/DS_TARGET_CSV')]"
			]
		},
		{
			"name": "[concat(parameters('factoryName'), '/PL_SQL_TO_ADLS')]",
			"type": "Microsoft.DataFactory/factories/pipelines",
			"apiVersion": "2018-06-01",
			"properties": {
				"activities": [
					{
						"name": "LookInfoTable",
						"type": "Lookup",
						"dependsOn": [],
						"policy": {
							"timeout": "0.12:00:00",
							"retry": 0,
							"retryIntervalInSeconds": 30,
							"secureOutput": false,
							"secureInput": false
						},
						"userProperties": [],
						"typeProperties": {
							"source": {
								"type": "AzureSqlSource",
								"sqlReaderQuery": "SELECT TABLE_SCHEMA, TABLE_NAME FROM INFORMATION_SCHEMA.TABLES WHERE TABLE_TYPE = 'BASE TABLE';",
								"queryTimeout": "02:00:00",
								"partitionOption": "None"
							},
							"dataset": {
								"referenceName": "DS_SQL_TABLES",
								"type": "DatasetReference",
								"parameters": {
									"SourceSchema": "''",
									"SourceTable": "''"
								}
							},
							"firstRowOnly": false
						}
					},
					{
						"name": "ForEachTable",
						"type": "ForEach",
						"dependsOn": [
							{
								"activity": "LookInfoTable",
								"dependencyConditions": [
									"Succeeded"
								]
							}
						],
						"userProperties": [],
						"typeProperties": {
							"items": {
								"value": "@activity('LookInfoTable').output.value",
								"type": "Expression"
							},
							"batchCount": 50,
							"activities": [
								{
									"name": "CopyData",
									"type": "Copy",
									"dependsOn": [],
									"policy": {
										"timeout": "0.12:00:00",
										"retry": 0,
										"retryIntervalInSeconds": 30,
										"secureOutput": false,
										"secureInput": false
									},
									"userProperties": [],
									"typeProperties": {
										"source": {
											"type": "AzureSqlSource",
											"queryTimeout": "02:00:00",
											"partitionOption": "None"
										},
										"sink": {
											"type": "ParquetSink",
											"storeSettings": {
												"type": "AzureBlobFSWriteSettings"
											},
											"formatSettings": {
												"type": "ParquetWriteSettings"
											}
										},
										"enableStaging": false,
										"translator": {
											"type": "TabularTranslator",
											"typeConversion": true,
											"typeConversionSettings": {
												"allowDataTruncation": true,
												"treatBooleanAsNumber": false
											}
										}
									},
									"inputs": [
										{
											"referenceName": "DS_SQL_TABLES",
											"type": "DatasetReference",
											"parameters": {
												"SourceSchema": {
													"value": "@item().TABLE_SCHEMA",
													"type": "Expression"
												},
												"SourceTable": {
													"value": "@item().TABLE_NAME",
													"type": "Expression"
												}
											}
										}
									],
									"outputs": [
										{
											"referenceName": "DS_SQL_TO_PARQUET",
											"type": "DatasetReference",
											"parameters": {
												"TargetFileName": {
													"value": "@concat(toLower(item().TABLE_NAME),formatDateTime(utcNow(), 'yyyyMMdd'))",
													"type": "Expression"
												}
											}
										}
									]
								}
							]
						}
					}
				],
				"policy": {
					"elapsedTimeMetric": {}
				},
				"annotations": []
			},
			"dependsOn": [
				"[concat(variables('factoryId'), '/datasets/DS_SQL_TABLES')]",
				"[concat(variables('factoryId'), '/datasets/DS_SQL_TO_PARQUET')]"
			]
		},
		{
			"name": "[concat(parameters('factoryName'), '/PL_SWITCH_CASE_DEMO')]",
			"type": "Microsoft.DataFactory/factories/pipelines",
			"apiVersion": "2018-06-01",
			"properties": {
				"activities": [
					{
						"name": "GetFiles",
						"type": "GetMetadata",
						"dependsOn": [],
						"policy": {
							"timeout": "0.12:00:00",
							"retry": 0,
							"retryIntervalInSeconds": 30,
							"secureOutput": false,
							"secureInput": false
						},
						"userProperties": [],
						"typeProperties": {
							"dataset": {
								"referenceName": "DS_FILE_LOOKUP",
								"type": "DatasetReference",
								"parameters": {}
							},
							"fieldList": [
								"childItems"
							],
							"storeSettings": {
								"type": "AzureBlobFSReadSettings",
								"recursive": true,
								"enablePartitionDiscovery": false
							},
							"formatSettings": {
								"type": "BinaryReadSettings"
							}
						}
					},
					{
						"name": "ForEachFile",
						"type": "ForEach",
						"dependsOn": [
							{
								"activity": "GetFiles",
								"dependencyConditions": [
									"Succeeded"
								]
							}
						],
						"userProperties": [],
						"typeProperties": {
							"items": {
								"value": "@activity('GetFiles').output.childItems",
								"type": "Expression"
							},
							"batchCount": 10,
							"activities": [
								{
									"name": "IfFile",
									"type": "IfCondition",
									"dependsOn": [],
									"userProperties": [],
									"typeProperties": {
										"expression": {
											"value": "@equals(item().type, 'File')",
											"type": "Expression"
										},
										"ifTrueActivities": [
											{
												"name": "SwitchCase",
												"type": "Switch",
												"dependsOn": [],
												"userProperties": [],
												"typeProperties": {
													"on": {
														"value": "@pipeline().parameters.FolderName",
														"type": "Expression"
													},
													"cases": [
														{
															"value": "RawDatasets",
															"activities": [
																{
																	"name": "CopyToRawDatasets",
																	"type": "Copy",
																	"dependsOn": [],
																	"policy": {
																		"timeout": "0.12:00:00",
																		"retry": 0,
																		"retryIntervalInSeconds": 30,
																		"secureOutput": false,
																		"secureInput": false
																	},
																	"userProperties": [],
																	"typeProperties": {
																		"source": {
																			"type": "BinarySource",
																			"storeSettings": {
																				"type": "AzureBlobFSReadSettings",
																				"recursive": true
																			},
																			"formatSettings": {
																				"type": "BinaryReadSettings"
																			}
																		},
																		"sink": {
																			"type": "BinarySink",
																			"storeSettings": {
																				"type": "AzureBlobFSWriteSettings"
																			}
																		},
																		"enableStaging": false
																	},
																	"inputs": [
																		{
																			"referenceName": "DS_SOURCE_FILE_POINTER",
																			"type": "DatasetReference",
																			"parameters": {
																				"SrcFileName": {
																					"value": "@item().name",
																					"type": "Expression"
																				}
																			}
																		}
																	],
																	"outputs": [
																		{
																			"referenceName": "DS_TARGET_FILE_POINTER",
																			"type": "DatasetReference",
																			"parameters": {
																				"TrgFileName": {
																					"value": "@item().name",
																					"type": "Expression"
																				},
																				"TrgFolderName": {
																					"value": "@pipeline().parameters.FolderName",
																					"type": "Expression"
																				}
																			}
																		}
																	]
																},
																{
																	"name": "DeleteFilesInRaw",
																	"type": "Delete",
																	"dependsOn": [
																		{
																			"activity": "CopyToRawDatasets",
																			"dependencyConditions": [
																				"Succeeded"
																			]
																		}
																	],
																	"policy": {
																		"timeout": "0.12:00:00",
																		"retry": 0,
																		"retryIntervalInSeconds": 30,
																		"secureOutput": false,
																		"secureInput": false
																	},
																	"userProperties": [],
																	"typeProperties": {
																		"dataset": {
																			"referenceName": "DS_SOURCE_FILE_POINTER",
																			"type": "DatasetReference",
																			"parameters": {
																				"SrcFileName": {
																					"value": "@item().name",
																					"type": "Expression"
																				}
																			}
																		},
																		"enableLogging": false,
																		"storeSettings": {
																			"type": "AzureBlobFSReadSettings",
																			"recursive": true,
																			"enablePartitionDiscovery": false
																		}
																	}
																}
															]
														},
														{
															"value": "StagedDatasets",
															"activities": [
																{
																	"name": "CopyInToStaged",
																	"type": "Copy",
																	"dependsOn": [],
																	"policy": {
																		"timeout": "0.12:00:00",
																		"retry": 0,
																		"retryIntervalInSeconds": 30,
																		"secureOutput": false,
																		"secureInput": false
																	},
																	"userProperties": [],
																	"typeProperties": {
																		"source": {
																			"type": "BinarySource",
																			"storeSettings": {
																				"type": "AzureBlobFSReadSettings",
																				"recursive": true
																			},
																			"formatSettings": {
																				"type": "BinaryReadSettings"
																			}
																		},
																		"sink": {
																			"type": "BinarySink",
																			"storeSettings": {
																				"type": "AzureBlobFSWriteSettings"
																			}
																		},
																		"enableStaging": false
																	},
																	"inputs": [
																		{
																			"referenceName": "DS_SOURCE_FILE_POINTER",
																			"type": "DatasetReference",
																			"parameters": {
																				"SrcFileName": {
																					"value": "@item().name",
																					"type": "Expression"
																				}
																			}
																		}
																	],
																	"outputs": [
																		{
																			"referenceName": "DS_TARGET_FILE_POINTER",
																			"type": "DatasetReference",
																			"parameters": {
																				"TrgFileName": {
																					"value": "@item().name",
																					"type": "Expression"
																				},
																				"TrgFolderName": {
																					"value": "@pipeline().parameters.FolderName",
																					"type": "Expression"
																				}
																			}
																		}
																	]
																},
																{
																	"name": "DeleteStaged",
																	"type": "Delete",
																	"dependsOn": [
																		{
																			"activity": "CopyInToStaged",
																			"dependencyConditions": [
																				"Succeeded"
																			]
																		}
																	],
																	"policy": {
																		"timeout": "0.12:00:00",
																		"retry": 0,
																		"retryIntervalInSeconds": 30,
																		"secureOutput": false,
																		"secureInput": false
																	},
																	"userProperties": [],
																	"typeProperties": {
																		"dataset": {
																			"referenceName": "DS_SOURCE_FILE_POINTER",
																			"type": "DatasetReference",
																			"parameters": {
																				"SrcFileName": {
																					"value": "@item().name",
																					"type": "Expression"
																				}
																			}
																		},
																		"enableLogging": false,
																		"storeSettings": {
																			"type": "AzureBlobFSReadSettings",
																			"recursive": true,
																			"enablePartitionDiscovery": false
																		}
																	}
																}
															]
														}
													]
												}
											}
										]
									}
								}
							]
						}
					}
				],
				"policy": {
					"elapsedTimeMetric": {}
				},
				"parameters": {
					"FolderName": {
						"type": "string",
						"defaultValue": "DefaultFolder"
					}
				},
				"annotations": []
			},
			"dependsOn": [
				"[concat(variables('factoryId'), '/datasets/DS_FILE_LOOKUP')]",
				"[concat(variables('factoryId'), '/datasets/DS_SOURCE_FILE_POINTER')]",
				"[concat(variables('factoryId'), '/datasets/DS_TARGET_FILE_POINTER')]"
			]
		},
		{
			"name": "[concat(parameters('factoryName'), '/DS_CSV_TARGET')]",
			"type": "Microsoft.DataFactory/factories/datasets",
			"apiVersion": "2018-06-01",
			"properties": {
				"linkedServiceName": {
					"referenceName": "LS_ADLS_CSV",
					"type": "LinkedServiceReference"
				},
				"folder": {
					"name": "ADLS_DATASETS"
				},
				"annotations": [],
				"type": "DelimitedText",
				"typeProperties": {
					"location": {
						"type": "AzureBlobFSLocation",
						"fileName": "bihar_election_results.csv",
						"folderPath": "ProcessedFiles",
						"fileSystem": "bronze-container"
					},
					"columnDelimiter": ",",
					"escapeChar": "\\",
					"firstRowAsHeader": true,
					"quoteChar": "\""
				},
				"schema": []
			},
			"dependsOn": [
				"[concat(variables('factoryId'), '/linkedServices/LS_ADLS_CSV')]"
			]
		},
		{
			"name": "[concat(parameters('factoryName'), '/DS_DYNAMIC_CSV_FILE_MIGRATION')]",
			"type": "Microsoft.DataFactory/factories/datasets",
			"apiVersion": "2018-06-01",
			"properties": {
				"linkedServiceName": {
					"referenceName": "LS_ADLS_CSV",
					"type": "LinkedServiceReference"
				},
				"parameters": {
					"FileName": {
						"type": "string"
					}
				},
				"folder": {
					"name": "ADLS_DATASETS"
				},
				"annotations": [],
				"type": "Binary",
				"typeProperties": {
					"location": {
						"type": "AzureBlobFSLocation",
						"fileName": {
							"value": "@dataset().FileName",
							"type": "Expression"
						},
						"fileSystem": "bronze-container"
					}
				}
			},
			"dependsOn": [
				"[concat(variables('factoryId'), '/linkedServices/LS_ADLS_CSV')]"
			]
		},
		{
			"name": "[concat(parameters('factoryName'), '/DS_DYNAMIC_CSV_FILE_MIGRATION_TARGET')]",
			"type": "Microsoft.DataFactory/factories/datasets",
			"apiVersion": "2018-06-01",
			"properties": {
				"linkedServiceName": {
					"referenceName": "LS_ADLS_CSV",
					"type": "LinkedServiceReference"
				},
				"parameters": {
					"TargetFileName": {
						"type": "string"
					}
				},
				"folder": {
					"name": "ADLS_DATASETS"
				},
				"annotations": [],
				"type": "Binary",
				"typeProperties": {
					"location": {
						"type": "AzureBlobFSLocation",
						"fileName": {
							"value": "@dataset().TargetFileName",
							"type": "Expression"
						},
						"folderPath": "ProcessedFiles",
						"fileSystem": "bronze-container"
					}
				}
			},
			"dependsOn": [
				"[concat(variables('factoryId'), '/linkedServices/LS_ADLS_CSV')]"
			]
		},
		{
			"name": "[concat(parameters('factoryName'), '/DS_FILE_LOOKUP')]",
			"type": "Microsoft.DataFactory/factories/datasets",
			"apiVersion": "2018-06-01",
			"properties": {
				"linkedServiceName": {
					"referenceName": "LS_ADLS_CSV",
					"type": "LinkedServiceReference"
				},
				"folder": {
					"name": "ADLS_DATASETS"
				},
				"annotations": [],
				"type": "Binary",
				"typeProperties": {
					"location": {
						"type": "AzureBlobFSLocation",
						"fileSystem": "bronze-container"
					}
				}
			},
			"dependsOn": [
				"[concat(variables('factoryId'), '/linkedServices/LS_ADLS_CSV')]"
			]
		},
		{
			"name": "[concat(parameters('factoryName'), '/DS_READ_CSV')]",
			"type": "Microsoft.DataFactory/factories/datasets",
			"apiVersion": "2018-06-01",
			"properties": {
				"linkedServiceName": {
					"referenceName": "LS_ADLS_CSV",
					"type": "LinkedServiceReference"
				},
				"folder": {
					"name": "ADLS_DATASETS"
				},
				"annotations": [],
				"type": "DelimitedText",
				"typeProperties": {
					"location": {
						"type": "AzureBlobFSLocation",
						"fileName": "bihar_election_results.csv",
						"fileSystem": "bronze-container"
					},
					"columnDelimiter": ",",
					"escapeChar": "\\",
					"firstRowAsHeader": true,
					"quoteChar": "\""
				},
				"schema": []
			},
			"dependsOn": [
				"[concat(variables('factoryId'), '/linkedServices/LS_ADLS_CSV')]"
			]
		},
		{
			"name": "[concat(parameters('factoryName'), '/DS_SOURCE_CSV')]",
			"type": "Microsoft.DataFactory/factories/datasets",
			"apiVersion": "2018-06-01",
			"properties": {
				"linkedServiceName": {
					"referenceName": "LS_ADLS_CSV",
					"type": "LinkedServiceReference"
				},
				"parameters": {
					"SourceFileName": {
						"type": "string"
					}
				},
				"folder": {
					"name": "ADLS_DATASETS"
				},
				"annotations": [],
				"type": "DelimitedText",
				"typeProperties": {
					"location": {
						"type": "AzureBlobFSLocation",
						"fileName": {
							"value": "@dataset().SourceFileName",
							"type": "Expression"
						},
						"folderPath": "RawFiles",
						"fileSystem": "bronze-container"
					},
					"columnDelimiter": ",",
					"escapeChar": "\\",
					"firstRowAsHeader": true,
					"quoteChar": "\""
				},
				"schema": []
			},
			"dependsOn": [
				"[concat(variables('factoryId'), '/linkedServices/LS_ADLS_CSV')]"
			]
		},
		{
			"name": "[concat(parameters('factoryName'), '/DS_SOURCE_FILE_POINTER')]",
			"type": "Microsoft.DataFactory/factories/datasets",
			"apiVersion": "2018-06-01",
			"properties": {
				"linkedServiceName": {
					"referenceName": "LS_ADLS_CSV",
					"type": "LinkedServiceReference"
				},
				"parameters": {
					"SrcFileName": {
						"type": "string"
					}
				},
				"folder": {
					"name": "ADLS_DATASETS"
				},
				"annotations": [],
				"type": "Binary",
				"typeProperties": {
					"location": {
						"type": "AzureBlobFSLocation",
						"fileName": {
							"value": "@dataset().SrcFileName",
							"type": "Expression"
						},
						"fileSystem": "bronze-container"
					}
				}
			},
			"dependsOn": [
				"[concat(variables('factoryId'), '/linkedServices/LS_ADLS_CSV')]"
			]
		},
		{
			"name": "[concat(parameters('factoryName'), '/DS_SQL_TABLES')]",
			"type": "Microsoft.DataFactory/factories/datasets",
			"apiVersion": "2018-06-01",
			"properties": {
				"linkedServiceName": {
					"referenceName": "LS_AZURE_SQL_DATABASE",
					"type": "LinkedServiceReference"
				},
				"parameters": {
					"SourceSchema": {
						"type": "string"
					},
					"SourceTable": {
						"type": "string"
					}
				},
				"folder": {
					"name": "SQL_DATASETS"
				},
				"annotations": [],
				"type": "AzureSqlTable",
				"schema": [],
				"typeProperties": {
					"schema": {
						"value": "@dataset().SourceSchema",
						"type": "Expression"
					},
					"table": {
						"value": "@dataset().SourceTable",
						"type": "Expression"
					}
				}
			},
			"dependsOn": [
				"[concat(variables('factoryId'), '/linkedServices/LS_AZURE_SQL_DATABASE')]"
			]
		},
		{
			"name": "[concat(parameters('factoryName'), '/DS_SQL_TO_PARQUET')]",
			"type": "Microsoft.DataFactory/factories/datasets",
			"apiVersion": "2018-06-01",
			"properties": {
				"linkedServiceName": {
					"referenceName": "LS_ADLS_CSV",
					"type": "LinkedServiceReference"
				},
				"parameters": {
					"TargetFileName": {
						"type": "string"
					}
				},
				"folder": {
					"name": "SQL_DATASETS"
				},
				"annotations": [],
				"type": "Parquet",
				"typeProperties": {
					"location": {
						"type": "AzureBlobFSLocation",
						"fileName": {
							"value": "@dataset().TargetFileName",
							"type": "Expression"
						},
						"folderPath": "SqlDatasets",
						"fileSystem": "bronze-container"
					},
					"compressionCodec": "snappy"
				},
				"schema": []
			},
			"dependsOn": [
				"[concat(variables('factoryId'), '/linkedServices/LS_ADLS_CSV')]"
			]
		},
		{
			"name": "[concat(parameters('factoryName'), '/DS_TARGET_CSV')]",
			"type": "Microsoft.DataFactory/factories/datasets",
			"apiVersion": "2018-06-01",
			"properties": {
				"linkedServiceName": {
					"referenceName": "LS_ADLS_CSV",
					"type": "LinkedServiceReference"
				},
				"parameters": {
					"TargetFileName": {
						"type": "string"
					}
				},
				"folder": {
					"name": "ADLS_DATASETS"
				},
				"annotations": [],
				"type": "DelimitedText",
				"typeProperties": {
					"location": {
						"type": "AzureBlobFSLocation",
						"fileName": {
							"value": "@dataset().TargetFileName",
							"type": "Expression"
						},
						"folderPath": "Processed",
						"fileSystem": "bronze-container"
					},
					"columnDelimiter": ",",
					"escapeChar": "\\",
					"firstRowAsHeader": true,
					"quoteChar": "\""
				},
				"schema": []
			},
			"dependsOn": [
				"[concat(variables('factoryId'), '/linkedServices/LS_ADLS_CSV')]"
			]
		},
		{
			"name": "[concat(parameters('factoryName'), '/DS_TARGET_FILE_POINTER')]",
			"type": "Microsoft.DataFactory/factories/datasets",
			"apiVersion": "2018-06-01",
			"properties": {
				"linkedServiceName": {
					"referenceName": "LS_ADLS_CSV",
					"type": "LinkedServiceReference"
				},
				"parameters": {
					"TrgFileName": {
						"type": "string"
					},
					"TrgFolderName": {
						"type": "string"
					}
				},
				"folder": {
					"name": "ADLS_DATASETS"
				},
				"annotations": [],
				"type": "Binary",
				"typeProperties": {
					"location": {
						"type": "AzureBlobFSLocation",
						"fileName": {
							"value": "@dataset().TrgFileName",
							"type": "Expression"
						},
						"folderPath": {
							"value": "@dataset().TrgFolderName",
							"type": "Expression"
						},
						"fileSystem": "bronze-container"
					}
				}
			},
			"dependsOn": [
				"[concat(variables('factoryId'), '/linkedServices/LS_ADLS_CSV')]"
			]
		},
		{
			"name": "[concat(parameters('factoryName'), '/LS_ADLS_CSV')]",
			"type": "Microsoft.DataFactory/factories/linkedServices",
			"apiVersion": "2018-06-01",
			"properties": {
				"annotations": [],
				"type": "AzureBlobFS",
				"typeProperties": {
					"url": "[parameters('LS_ADLS_CSV_properties_typeProperties_url')]",
					"accountKey": {
						"type": "SecureString",
						"value": "[parameters('LS_ADLS_CSV_accountKey')]"
					}
				}
			},
			"dependsOn": []
		},
		{
			"name": "[concat(parameters('factoryName'), '/LS_AZURE_SQL_DATABASE')]",
			"type": "Microsoft.DataFactory/factories/linkedServices",
			"apiVersion": "2018-06-01",
			"properties": {
				"annotations": [],
				"type": "AzureSqlDatabase",
				"typeProperties": {
					"server": "[parameters('LS_AZURE_SQL_DATABASE_properties_typeProperties_server')]",
					"database": "[parameters('LS_AZURE_SQL_DATABASE_properties_typeProperties_database')]",
					"encrypt": "mandatory",
					"trustServerCertificate": true,
					"authenticationType": "SQL",
					"userName": "[parameters('LS_AZURE_SQL_DATABASE_properties_typeProperties_userName')]",
					"password": {
						"type": "SecureString",
						"value": "[parameters('LS_AZURE_SQL_DATABASE_password')]"
					}
				}
			},
			"dependsOn": []
		},
		{
			"name": "[concat(parameters('factoryName'), '/MyEventBasedTrigger')]",
			"type": "Microsoft.DataFactory/factories/triggers",
			"apiVersion": "2018-06-01",
			"properties": {
				"annotations": [],
				"runtimeState": "Started",
				"pipelines": [
					{
						"pipelineReference": {
							"referenceName": "PL_EVENT_BASED_MIGRATION",
							"type": "PipelineReference"
						},
						"parameters": {
							"FileName": "[parameters('MyEventBasedTrigger_properties_PL_EVENT_BASED_MIGRATION_parameters_FileName')]"
						}
					}
				],
				"type": "BlobEventsTrigger",
				"typeProperties": {
					"blobPathBeginsWith": "/bronze-container/blobs/RawFiles/",
					"blobPathEndsWith": ".csv",
					"ignoreEmptyBlobs": true,
					"scope": "[parameters('MyEventBasedTrigger_properties_typeProperties_scope')]",
					"events": [
						"Microsoft.Storage.BlobCreated"
					]
				}
			},
			"dependsOn": [
				"[concat(variables('factoryId'), '/pipelines/PL_EVENT_BASED_MIGRATION')]"
			]
		}
	]
}